serial_teleinfo/__init__.py
serial_teleinfo/client.py
serial_teleinfo/exception.py
serial_teleinfo/parser.py
serial_teleinfo/types.py
serial_teleinfo/updater.py
serial_teleinfo/server/__init__.py
serial_teleinfo/server/__main__.py
serial_teleinfo/server/routes.py
serial_teleinfo/server/server.py
serial_teleinfo-1.0.1.dist-info/LICENSE
serial_teleinfo-1.0.1.dist-info/METADATA
serial_teleinfo-1.0.1.dist-info/WHEEL
serial_teleinfo-1.0.1.dist-info/top_level.txt
serial_teleinfo-1.0.1.dist-info/RECORD
