Metadata-Version: 2.1
Name: serial-teleinfo
Version: 1.0.1
Summary: Utilities to connect to a Teleinformation serial device
Home-page: https://github.com/ugomeda/serial-teleinfo
Author: Ugo Méda
Author-email: meda.ugo@gmail.com
License: UNKNOWN
Platform: UNKNOWN
Classifier: Programming Language :: Python :: 3
Classifier: License :: OSI Approved :: MIT License
Classifier: Operating System :: OS Independent
Requires-Python: >=3.7
Requires-Dist: pyserial
Provides-Extra: server
Requires-Dist: aiohttp ; extra == 'server'
Requires-Dist: http-basic-auth ; extra == 'server'
